dynamo/__init__.py
dynamo/bibtex.py
dynamo/constants.py
dynamo/icon.png
dynamo/protocols.conf
dynamo/utils.py
dynamo/wizards.py
dynamo/convert/__init__.py
dynamo/convert/convert.py
dynamo/protocols/__init__.py
dynamo/protocols/protocol_average_subtomograms.py
dynamo/protocols/protocol_base_dynamo.py
dynamo/protocols/protocol_bin_tomograms.py
dynamo/protocols/protocol_boxing.py
dynamo/protocols/protocol_coords_to_model.py
dynamo/protocols/protocol_extraction.py
dynamo/protocols/protocol_import_subtomos.py
dynamo/protocols/protocol_import_tomograms.py
dynamo/protocols/protocol_model_workflow.py
dynamo/protocols/protocol_subBoxing.py
dynamo/protocols/protocol_subtomo_MRA.py
dynamo/tests/__init__.py
dynamo/tests/_test_dynamo_refinement.py
dynamo/tests/test_dynamo_align_subtomos.py
dynamo/tests/test_dynamo_average_subtomos.py
dynamo/tests/test_dynamo_base.py
dynamo/tests/test_dynamo_bin_tomograms.py
dynamo/tests/test_dynamo_extraction.py
dynamo/tests/test_dynamo_import_subtomograms.py
dynamo/tests/test_dynamo_model_workflow.py
dynamo/viewers/DynamoTomoProvider.py
dynamo/viewers/__init__.py
dynamo/viewers/viewers_data.py
dynamo/viewers/views_tkinter_tree.py
scipion_em_dynamo-3.3.1.dist-info/LICENSE
scipion_em_dynamo-3.3.1.dist-info/METADATA
scipion_em_dynamo-3.3.1.dist-info/WHEEL
scipion_em_dynamo-3.3.1.dist-info/entry_points.txt
scipion_em_dynamo-3.3.1.dist-info/top_level.txt
scipion_em_dynamo-3.3.1.dist-info/RECORD
